{
  "branch_name": "feat/browser-clipper",
  "completion_review_status": "ship",
  "completion_reviewed_at": "2026-07-24T12:31:02.011481Z",
  "created_at": "2026-07-21T21:34:04.205056Z",
  "default_impl": null,
  "default_review": null,
  "default_sync": null,
  "depends_on_epics": [
    "fn-105-verified-folder-setup"
  ],
  "id": "fn-106-browser-clipper-with-provenance",
  "impl_review_rounds": {},
  "next_task": 1,
  "plan_review_rounds": 0,
  "plan_review_status": "unknown",
  "plan_reviewed_at": null,
  "spec_path": ".flow/specs/fn-106-browser-clipper-with-provenance.md",
  "status": "done",
  "title": "Browser Clipper with Provenance",
  "tracker": {
    "baseHashFlow": "7a11441521e87cba96908d773045a44ed223bf4a6571d3ef9574ab9c851e24f7",
    "baseHashTracker": "8f6f661e937e9a6892d067c77e18c485fdc782a02e45125aa0efe4d2502be67d",
    "depRelations": [
      {
        "dep_spec": "fn-105-verified-folder-setup",
        "from_tracker_id": "GNO-18",
        "key": "1f946ae82cc52171",
        "source": "flow",
        "to_tracker_id": "GNO-16",
        "type": "blocks",
        "updatedAt": "2026-07-21T22:14:07.777119Z"
      }
    ],
    "id": "GNO-18",
    "identifier": "GNO-18",
    "lastSyncedAt": "2026-07-24T14:15:24.472316Z",
    "mergeBaseFlow": "# fn-106 Browser Clipper with Provenance\n\n## Goal & Context\n<!-- scope: business -->\n\nLet users capture a selected passage or clean Reader-style article from the browser into GNO with a preview and trustworthy provenance. Prefer a small local-first clipper over broad browser-history or OAuth connector access.\n\n## Architecture & Data Models\n<!-- scope: technical -->\n\nCreate a minimal browser extension sharing one capture payload contract with GNO's existing core:\n\n- selection or sanitized Reader extraction\n- source URL, canonical URL, page title, author/site, published/observed/captured dates\n- capture mode, browser metadata, optional user note/tags/target collection/folder\n- source hash and extraction warnings\n\nPair the extension to the loopback resident gateway using a short-lived, user-approved token. A preview shows exact content/frontmatter and destination before write. The gateway validates Origin/token/payload size, sanitizes HTML to canonical Markdown through the converter/capture pipeline, and returns the normal capture receipt.\n\n## API Contracts\n<!-- scope: technical -->\n\n- Loopback pairing endpoints create/revoke scoped clipper tokens after visible user consent.\n- `POST /api/capture/clip` accepts the versioned clip payload and returns existing capture/sync/embed receipt semantics plus provenance warnings.\n- Extension supports selection and Reader modes, preview/edit, destination/tags, success/error receipt, and token revocation.\n- No public/non-loopback clip endpoint without later auth/egress work.\n\n## Edge Cases & Constraints\n<!-- scope: technical -->\n\n- Sanitize scripts/styles/forms/hidden tracking content and reject dangerous schemes.\n- Handle paywalls/authenticated pages by capturing only browser-visible user-selected content; never bypass access controls.\n- Canonical URL loops, duplicate clips, huge pages, images/data URLs, iframes, SPAs, offline gateway, token expiry, and Unicode need explicit behavior.\n- Treat clipped text as untrusted content in later prompts.\n- Pairing is CSRF/Origin protected, loopback-only, least-privilege, revocable, and rate-limited.\n\n## Acceptance Criteria\n<!-- scope: both -->\n\n- **R1:** A user can select text or choose Reader extraction, preview/edit it, select destination/tags, and create a GNO note with one confirmation.\n- **R2:** Captured notes carry normalized source URL/title/dates/mode/hash provenance through the existing capture receipt path.\n- **R3:** Pairing tokens are short-lived/scoped/revocable; Origin/CSRF/rate-limit tests block unauthorized local-web requests.\n- **R4:** Sanitization fixtures remove executable/tracking content while preserving readable structure and exact selected text.\n- **R5:** Duplicate, huge, authenticated-visible, SPA, offline, expiry, and Unicode cases return actionable receipts without silent data loss.\n- **R6:** Extension packaging, permissions, privacy disclosure, local gateway docs, and end-to-end browser tests are complete.\n\n## Boundaries\n<!-- scope: business -->\n\nNo browsing-history ingestion, cookie/session export, paywall bypass, cloud sync, OAuth connector, background surveillance, or autonomous clipping.\n\n## Decision Context\n<!-- scope: both \u2014 conditionally substructured -->\n\n### Motivation\n<!-- scope: business -->\n\nWeb evidence is a common input to a knowledge base. A previewed local clipper closes that capture gap with much less trust surface than account-wide connectors.\n\n### Implementation Tradeoffs\n<!-- scope: technical -->\n\nA browser extension offers reliable selection/Reader access but requires careful local pairing. Reusing capture provenance avoids creating a second ingestion model.\n\n## Implementation Plan\n\n1. `fn-106-browser-clipper-with-provenance.1` \u2014 Define clip payload sanitization and capture provenance (**M**)\n2. `fn-106-browser-clipper-with-provenance.2` \u2014 Add secure loopback clipper pairing and capture endpoints (**M**); depends on `fn-106-browser-clipper-with-provenance.1`\n3. `fn-106-browser-clipper-with-provenance.3` \u2014 Build the minimal browser extension preview workflow (**M**); depends on `fn-106-browser-clipper-with-provenance.1`, `fn-106-browser-clipper-with-provenance.2`\n4. `fn-106-browser-clipper-with-provenance.4` \u2014 Package test and document the local clipper (**M**); depends on `fn-106-browser-clipper-with-provenance.3`\n\n## Quick commands\n\n```bash\nbun test test/clipper test/capture\nbun run test:e2e\n.flow/bin/flowctl validate --spec fn-106-browser-clipper-with-provenance --json\n```\n\n## References\n\n- [MDN extension content safety](https://developer.mozilla.org/en-US/docs/Mozilla/Add-ons/WebExtensions/Safely_inserting_external_content_into_a_page).\n- `src/core/capture.ts:53-120` and `:627-744` \u2014 capture plan/receipt.\n- `src/serve/routes/api.ts:2869-3020` \u2014 local capture API.\n\n## Early proof point\n\nTask `fn-106-browser-clipper-with-provenance.1` validates the core approach (a versioned selected-text payload round-trips through existing capture provenance without executable HTML or ambiguous source hashing).\nIf it fails, re-evaluate the clip payload/edit provenance and sanitization boundary before continuing with `fn-106-browser-clipper-with-provenance.2`+.\n\n## Requirement coverage\n\n| Req | Description | Task(s) | Gap justification |\n|-----|-------------|---------|-------------------|\n| R1 | A user can select text or choose Reader extraction, preview/edit it, select destination/tags, and create a GNO note with one confirmation. | fn-106-browser-clipper-with-provenance.3, fn-106-browser-clipper-with-provenance.4 | \u2014 |\n| R2 | Captured notes carry normalized source URL/title/dates/mode/hash provenance through the existing capture receipt path. | fn-106-browser-clipper-with-provenance.1 | \u2014 |\n| R3 | Pairing tokens are short-lived/scoped/revocable; Origin/CSRF/rate-limit tests block unauthorized local-web requests. | fn-106-browser-clipper-with-provenance.2, fn-106-browser-clipper-with-provenance.4 | \u2014 |\n| R4 | Sanitization fixtures remove executable/tracking content while preserving readable structure and exact selected text. | fn-106-browser-clipper-with-provenance.1, fn-106-browser-clipper-with-provenance.4 | \u2014 |\n| R5 | Duplicate, huge, authenticated-visible, SPA, offline, expiry, and Unicode cases return actionable receipts without silent data loss. | fn-106-browser-clipper-with-provenance.1, fn-106-browser-clipper-with-provenance.2, fn-106-browser-clipper-with-provenance.3, fn-106-browser-clipper-with-provenance.4 | \u2014 |\n| R6 | Extension packaging, permissions, privacy disclosure, local gateway docs, and end-to-end browser tests are complete. | fn-106-browser-clipper-with-provenance.3, fn-106-browser-clipper-with-provenance.4 | \u2014 |\n",
    "mergeBaseTracker": "# fn-106 Browser Clipper with Provenance\n\n## Goal & Context\n\n<!-- scope: business -->\n\nLet users capture a selected passage or clean Reader-style article from the browser into GNO with a preview and trustworthy provenance. Prefer a small local-first clipper over broad browser-history or OAuth connector access.\n\n## Architecture & Data Models\n\n<!-- scope: technical -->\n\nCreate a minimal browser extension sharing one capture payload contract with GNO's existing core:\n\n* selection or sanitized Reader extraction\n* source URL, canonical URL, page title, author/site, published/observed/captured dates\n* capture mode, browser metadata, optional user note/tags/target collection/folder\n* source hash and extraction warnings\n\nPair the extension to the loopback resident gateway using a short-lived, user-approved token. A preview shows exact content/frontmatter and destination before write. The gateway validates Origin/token/payload size, sanitizes HTML to canonical Markdown through the converter/capture pipeline, and returns the normal capture receipt.\n\n## API Contracts\n\n<!-- scope: technical -->\n\n* Loopback pairing endpoints create/revoke scoped clipper tokens after visible user consent.\n* `POST /api/capture/clip` accepts the versioned clip payload and returns existing capture/sync/embed receipt semantics plus provenance warnings.\n* Extension supports selection and Reader modes, preview/edit, destination/tags, success/error receipt, and token revocation.\n* No public/non-loopback clip endpoint without later auth/egress work.\n\n## Edge Cases & Constraints\n\n<!-- scope: technical -->\n\n* Sanitize scripts/styles/forms/hidden tracking content and reject dangerous schemes.\n* Handle paywalls/authenticated pages by capturing only browser-visible user-selected content; never bypass access controls.\n* Canonical URL loops, duplicate clips, huge pages, images/data URLs, iframes, SPAs, offline gateway, token expiry, and Unicode need explicit behavior.\n* Treat clipped text as untrusted content in later prompts.\n* Pairing is CSRF/Origin protected, loopback-only, least-privilege, revocable, and rate-limited.\n\n## Acceptance Criteria\n\n<!-- scope: both -->\n\n* **R1:** A user can select text or choose Reader extraction, preview/edit it, select destination/tags, and create a GNO note with one confirmation.\n* **R2:** Captured notes carry normalized source URL/title/dates/mode/hash provenance through the existing capture receipt path.\n* **R3:** Pairing tokens are short-lived/scoped/revocable; Origin/CSRF/rate-limit tests block unauthorized local-web requests.\n* **R4:** Sanitization fixtures remove executable/tracking content while preserving readable structure and exact selected text.\n* **R5:** Duplicate, huge, authenticated-visible, SPA, offline, expiry, and Unicode cases return actionable receipts without silent data loss.\n* **R6:** Extension packaging, permissions, privacy disclosure, local gateway docs, and end-to-end browser tests are complete.\n\n## Boundaries\n\n<!-- scope: business -->\n\nNo browsing-history ingestion, cookie/session export, paywall bypass, cloud sync, OAuth connector, background surveillance, or autonomous clipping.\n\n## Decision Context\n\n<!-- scope: both \u2014 conditionally substructured -->\n\n### Motivation\n\n<!-- scope: business -->\n\nWeb evidence is a common input to a knowledge base. A previewed local clipper closes that capture gap with much less trust surface than account-wide connectors.\n\n### Implementation Tradeoffs\n\n<!-- scope: technical -->\n\nA browser extension offers reliable selection/Reader access but requires careful local pairing. Reusing capture provenance avoids creating a second ingestion model.\n\n## Implementation Plan\n\n1. `fn-106-browser-clipper-with-provenance.1` \u2014 Define clip payload sanitization and capture provenance (**M**)\n2. `fn-106-browser-clipper-with-provenance.2` \u2014 Add secure loopback clipper pairing and capture endpoints (**M**); depends on `fn-106-browser-clipper-with-provenance.1`\n3. `fn-106-browser-clipper-with-provenance.3` \u2014 Build the minimal browser extension preview workflow (**M**); depends on `fn-106-browser-clipper-with-provenance.1`, `fn-106-browser-clipper-with-provenance.2`\n4. `fn-106-browser-clipper-with-provenance.4` \u2014 Package test and document the local clipper (**M**); depends on `fn-106-browser-clipper-with-provenance.3`\n\n## Quick commands\n\n```bash\nbun test test/clipper test/capture\nbun run test:e2e\n.flow/bin/flowctl validate --spec fn-106-browser-clipper-with-provenance --json\n```\n\n## References\n\n* [MDN extension content safety](<https://developer.mozilla.org/en-US/docs/Mozilla/Add-ons/WebExtensions/Safely_inserting_external_content_into_a_page>).\n* `src/core/capture.ts:53-120` and `:627-744` \u2014 capture plan/receipt.\n* `src/serve/routes/api.ts:2869-3020` \u2014 local capture API.\n\n## Early proof point\n\nTask `fn-106-browser-clipper-with-provenance.1` validates the core approach (a versioned selected-text payload round-trips through existing capture provenance without executable HTML or ambiguous source hashing).\nIf it fails, re-evaluate the clip payload/edit provenance and sanitization boundary before continuing with `fn-106-browser-clipper-with-provenance.2`+.\n\n## Requirement coverage\n\n| Req | Description | Task(s) | Gap justification |\n| -- | -- | -- | -- |\n| R1 | A user can select text or choose Reader extraction, preview/edit it, select destination/tags, and create a GNO note with one confirmation. | fn-106-browser-clipper-with-provenance.3, fn-106-browser-clipper-with-provenance.4 | \u2014 |\n| R2 | Captured notes carry normalized source URL/title/dates/mode/hash provenance through the existing capture receipt path. | fn-106-browser-clipper-with-provenance.1 | \u2014 |\n| R3 | Pairing tokens are short-lived/scoped/revocable; Origin/CSRF/rate-limit tests block unauthorized local-web requests. | fn-106-browser-clipper-with-provenance.2, fn-106-browser-clipper-with-provenance.4 | \u2014 |\n| R4 | Sanitization fixtures remove executable/tracking content while preserving readable structure and exact selected text. | fn-106-browser-clipper-with-provenance.1, fn-106-browser-clipper-with-provenance.4 | \u2014 |\n| R5 | Duplicate, huge, authenticated-visible, SPA, offline, expiry, and Unicode cases return actionable receipts without silent data loss. | fn-106-browser-clipper-with-provenance.1, fn-106-browser-clipper-with-provenance.2, fn-106-browser-clipper-with-provenance.3, fn-106-browser-clipper-with-provenance.4 | \u2014 |\n| R6 | Extension packaging, permissions, privacy disclosure, local gateway docs, and end-to-end browser tests are complete. | fn-106-browser-clipper-with-provenance.3, fn-106-browser-clipper-with-provenance.4 | \u2014 |\n",
    "url": "https://linear.app/gmickel/issue/GNO-18"
  },
  "updated_at": "2026-07-24T14:15:24.473090Z"
}
