{
  "branch_name": "fn-48-desktop-beta-background-service-and",
  "completion_review_status": "unknown",
  "completion_reviewed_at": null,
  "created_at": "2026-03-22T14:55:28.776252Z",
  "default_impl": null,
  "default_review": null,
  "default_sync": null,
  "depends_on_epics": [
    "fn-41-document-workspace-foundation-for",
    "fn-42-desktop-beta-onboarding-and-health"
  ],
  "id": "fn-48-desktop-beta-background-service-and",
  "next_task": 1,
  "plan_review_status": "unknown",
  "plan_reviewed_at": null,
  "spec_path": ".flow/specs/fn-48-desktop-beta-background-service-and.md",
  "status": "done",
  "title": "Desktop Beta: Background Service and Watch Hardening",
  "updated_at": "2026-04-02T19:31:21.981704Z"
}
